./.gitignore
./PKG-INFO
./README.md
./REQUIREMENTS.md
./mcp_server.py
./pyproject.toml
./uv.lock
search_mcp_server-0.2.0.dist-info/METADATA
search_mcp_server-0.2.0.dist-info/WHEEL
search_mcp_server-0.2.0.dist-info/entry_points.txt
search_mcp_server-0.2.0.dist-info/RECORD
