Metadata-Version: 2.4
Name: search-mcp-server
Version: 0.2.0
Summary: A Model Context Protocol (MCP) search server
Project-URL: Homepage, https://github.com/krzysztofkucmierz/search-mcp-server
Project-URL: Repository, https://github.com/krzysztofkucmierz/search-mcp-server
Project-URL: Issues, https://github.com/krzysztofkucmierz/search-mcp-server/issues
Author-email: Krzysztof Kućmierz <krzysztof.kucmierz@artificiuminformatica.pl>
License: Apache 2.0
Classifier: Development Status :: 4 - Beta
Classifier: Intended Audience :: Developers
Classifier: License :: OSI Approved :: MIT License
Classifier: Programming Language :: Python :: 3
Classifier: Programming Language :: Python :: 3.13
Requires-Python: >=3.13
Requires-Dist: beautifulsoup4
Requires-Dist: fastmcp>=2.11.3
Requires-Dist: httpx
Requires-Dist: lxml
